pythondata_cpu_minerva/__init__.py
pythondata_cpu_minerva/sources/.env.toolchain
pythondata_cpu_minerva/sources/.gitignore
pythondata_cpu_minerva/sources/LICENSE.txt
pythondata_cpu_minerva/sources/README.md
pythondata_cpu_minerva/sources/cli.py
pythondata_cpu_minerva/sources/pyproject.toml
pythondata_cpu_minerva/sources/setup.py
pythondata_cpu_minerva/sources/minerva/__init__.py
pythondata_cpu_minerva/sources/minerva/arbiter.py
pythondata_cpu_minerva/sources/minerva/cache.py
pythondata_cpu_minerva/sources/minerva/core.py
pythondata_cpu_minerva/sources/minerva/gpr.py
pythondata_cpu_minerva/sources/minerva/isa.py
pythondata_cpu_minerva/sources/minerva/stage.py
pythondata_cpu_minerva/sources/minerva/csr/__init__.py
pythondata_cpu_minerva/sources/minerva/csr/action.py
pythondata_cpu_minerva/sources/minerva/csr/reg.py
pythondata_cpu_minerva/sources/minerva/test/__init__.py
pythondata_cpu_minerva/sources/minerva/test/utils.py
pythondata_cpu_minerva/sources/minerva/units/__init__.py
pythondata_cpu_minerva/sources/minerva/units/adder.py
pythondata_cpu_minerva/sources/minerva/units/compare.py
pythondata_cpu_minerva/sources/minerva/units/decoder.py
pythondata_cpu_minerva/sources/minerva/units/divider.py
pythondata_cpu_minerva/sources/minerva/units/exception.py
pythondata_cpu_minerva/sources/minerva/units/fetch.py
pythondata_cpu_minerva/sources/minerva/units/loadstore.py
pythondata_cpu_minerva/sources/minerva/units/logic.py
pythondata_cpu_minerva/sources/minerva/units/multiplier.py
pythondata_cpu_minerva/sources/minerva/units/predict.py
pythondata_cpu_minerva/sources/minerva/units/rvficon.py
pythondata_cpu_minerva/sources/minerva/units/shifter.py
pythondata_cpu_minerva/sources/tests/__init__.py
pythondata_cpu_minerva/sources/tests/test_cache.py
pythondata_cpu_minerva/sources/tests/test_units_divider.py
pythondata_cpu_minerva/sources/tests/test_units_multiplier.py
pythondata_cpu_minerva-0.0.post294.dist-info/LICENSE
pythondata_cpu_minerva-0.0.post294.dist-info/METADATA
pythondata_cpu_minerva-0.0.post294.dist-info/WHEEL
pythondata_cpu_minerva-0.0.post294.dist-info/top_level.txt
pythondata_cpu_minerva-0.0.post294.dist-info/RECORD
