Metadata-Version: 2.2
Name: pythondata-cpu-minerva
Version: 0.0.post294
Summary: Python module containing sources files for Minerva cpu.
Home-page: https://github.com/litex-hub/pythondata-cpu-minerva
Author: LiteX Authors
Author-email: litex@googlegroups.com
Project-URL: Bug Tracker, https://github.com/litex-hub/pythondata-cpu-minerva/issues
Project-URL: Source Code, https://github.com/litex-hub/pythondata-cpu-minerva
Classifier: Programming Language :: Python :: 3
Classifier: License :: OSI Approved :: BSD License
Classifier: Operating System :: OS Independent
Requires-Python: >=3.5
License-File: LICENSE
Dynamic: author
Dynamic: author-email
Dynamic: classifier
Dynamic: description
Dynamic: description-content-type
Dynamic: home-page
Dynamic: project-url
Dynamic: requires-python
Dynamic: summary
